Metadata-Version: 2.1
Name: bootleg
Version: 1.1.0
Summary: Bootleg NED System
Home-page: https://github.com/HazyResearch/bootleg
License: UNKNOWN
Platform: UNKNOWN
License-File: LICENSE
Requires-Dist: argh (<1.0.0,>=0.26.2)
Requires-Dist: click (<7.5.0,>=7.1.2)
Requires-Dist: emmental (==0.1.0)
Requires-Dist: faiss-cpu (<1.7.1,>=1.6.8)
Requires-Dist: jsonlines (<2.4.0,>=2.0.0)
Requires-Dist: marisa-trie (<0.8,>=0.7.7)
Requires-Dist: mock (<4.5.0,>=4.0.3)
Requires-Dist: nltk (<4.0.0,>=3.6.4)
Requires-Dist: notebook (<7.0.0,>=6.4.1)
Requires-Dist: numba (<0.55.0,>=0.50.0)
Requires-Dist: numpy (<=1.20.0,>=1.19.0)
Requires-Dist: pandas (<1.5.0,>=1.2.3)
Requires-Dist: progressbar (<2.8.0,>=2.5.0)
Requires-Dist: pydantic (<1.8.0,>=1.7.1)
Requires-Dist: pyyaml (<6.0,>=5.1)
Requires-Dist: rich (<10.20.0,>=10.0.0)
Requires-Dist: scikit-learn (<0.27.0,>=0.24.0)
Requires-Dist: scipy (<1.9.0,>=1.6.1)
Requires-Dist: sentencepiece (==0.1.*)
Requires-Dist: spacy (==3.0.1)
Requires-Dist: tagme (<0.2.0,>=0.1.3)
Requires-Dist: torch (<1.10.5,>=1.7.0)
Requires-Dist: tqdm (>=4.27)
Requires-Dist: transformers (<5.0.0,>=4.0.0)
Requires-Dist: ujson (<4.2.0,>=4.1.0)
Requires-Dist: wandb (<0.13.0,>=0.10.0)
Provides-Extra: dev
Requires-Dist: black (>=21.7b0) ; extra == 'dev'
Requires-Dist: docformatter (==1.4) ; extra == 'dev'
Requires-Dist: flake8 (>=3.9.2) ; extra == 'dev'
Requires-Dist: isort (>=5.9.3) ; extra == 'dev'
Requires-Dist: nbsphinx (==0.8.1) ; extra == 'dev'
Requires-Dist: pep8-naming (==0.12.1) ; extra == 'dev'
Requires-Dist: pre-commit (>=2.14.0) ; extra == 'dev'
Requires-Dist: pytest (==6.2.2) ; extra == 'dev'
Requires-Dist: python-dotenv (==0.15.0) ; extra == 'dev'
Requires-Dist: recommonmark (==0.7.1) ; extra == 'dev'
Requires-Dist: sphinx-rtd-theme (==0.5.1) ; extra == 'dev'
Provides-Extra: embs-gpu
Requires-Dist: faiss-gpu (<1.7.2,>=1.7.0) ; extra == 'embs-gpu'
